oboframework/__init__.py
oboframework/app.py
oboframework/middleware.py
oboframework/response.py
oboframework-0.1.2.dist-info/METADATA
oboframework-0.1.2.dist-info/WHEEL
oboframework-0.1.2.dist-info/top_level.txt
oboframework-0.1.2.dist-info/RECORD
