Metadata-Version: 2.1
Name: oboframework
Version: 0.1.2
Summary: Python Web Framework built for learning purpose
Home-page: https://github.com/me/myproject
Author: Otajon Bozorboev
Author-email: otajonbozorboyev571@gmail.com
License: MIT
Classifier: License :: OSI Approved :: MIT License
Classifier: Programming Language :: Python
Classifier: Programming Language :: Python :: 3
Classifier: Programming Language :: Python :: 3.6
Classifier: Programming Language :: Python :: Implementation :: CPython
Classifier: Programming Language :: Python :: Implementation :: PyPy
Requires-Python: >=3.11.3
Requires-Dist: Jinja2==3.1.6
Requires-Dist: parse==1.20.2
Requires-Dist: requests==2.32.3
Requires-Dist: requests-wsgi-adapter==0.4.1
Requires-Dist: WebOb==1.8.9
Requires-Dist: whitenoise==6.9.0
